celery_chain_router/__init__.py
celery_chain_router/router.py
celery_chain_router/utils.py
celery_chain_router/examples/__init__.py
celery_chain_router/examples/simple_example.py
celery_chain_router/examples/tasks.py
celery_chain_router-0.2.0.dist-info/licenses/LICENSE
celery_chain_router-0.2.0.dist-info/METADATA
celery_chain_router-0.2.0.dist-info/WHEEL
celery_chain_router-0.2.0.dist-info/top_level.txt
celery_chain_router-0.2.0.dist-info/RECORD
