Metadata-Version: 2.4
Name: celery-chain-router
Version: 0.2.0
Summary: A Celery router that uses consistent hashing for data locality
Home-page: https://github.com/petritavd/celery-chain-router
Author: Petrit Avdylaj
Author-email: Petrit Avdylaj <petritavd@gmail.com>
License-Expression: MIT
Project-URL: Homepage, https://github.com/petritavd/celery-chain-router
Project-URL: Bug Tracker, https://github.com/petritavd/celery-chain-router/issues
Classifier: Programming Language :: Python :: 3
Classifier: Operating System :: OS Independent
Classifier: Topic :: Software Development :: Libraries :: Python Modules
Classifier: Framework :: Celery
Requires-Python: >=3.6
License-File: LICENSE
Requires-Dist: celery>=5.0.0
Requires-Dist: redis>=3.5.0
Provides-Extra: dev
Requires-Dist: pytest>=6.0.0; extra == "dev"
Requires-Dist: pytest-cov>=2.10.0; extra == "dev"
Requires-Dist: black>=20.8b1; extra == "dev"
Requires-Dist: flake8>=3.8.0; extra == "dev"
Dynamic: author
Dynamic: home-page
Dynamic: license-file
Dynamic: requires-python
